l10n/__init__.py
l10n/__main__.py
l10n/_cli.py
l10n/_extractor.py
l10n/_locale.py
l10n/_locales.py
l10n/_plurals.py
l10n/_project.py
l10n/py.typed
l10n/_commands/__init__.py
l10n/_commands/_base.py
l10n/_commands/_compile.py
l10n/_commands/_extract.py
l10n/_commands/_translate.py
l10n-0.1.4.dist-info/entry_points.txt
l10n-0.1.4.dist-info/LICENSE
l10n-0.1.4.dist-info/WHEEL
l10n-0.1.4.dist-info/METADATA
l10n-0.1.4.dist-info/RECORD
