Metadata-Version: 2.1
Name: l10n
Version: 0.1.4
Summary: A library and CLI for translating Python applications and libraries.
Keywords: localization,internationalization,l10n,i18n,locale,locales,translation,gettext
Author-email: Gram <gram@orsinium.dev>
Requires-Python: >=3.7
Classifier: Development Status :: 5 - Production/Stable
Classifier: Intended Audience :: Developers
Classifier: License :: OSI Approved :: MIT License
Classifier: Programming Language :: Python
Classifier: Topic :: Software Development
Classifier: Topic :: Software Development :: Internationalization
Classifier: Topic :: Software Development :: Localization
Classifier: Topic :: Text Processing :: Linguistic
Classifier: Typing :: Typed
Requires-Dist: mypy ; extra == "cli"
Requires-Dist: tomli ; extra == "cli"
Requires-Dist: polib ; extra == "cli"
Requires-Dist: sphinx ; extra == "docs"
Requires-Dist: myst-parser ; extra == "docs"
Requires-Dist: flake8-length ; extra == "lint"
Requires-Dist: flake8 ; extra == "lint"
Requires-Dist: isort ; extra == "lint"
Requires-Dist: mypy ; extra == "lint"
Requires-Dist: types-polib ; extra == "lint"
Requires-Dist: types-toml ; extra == "lint"
Requires-Dist: unify ; extra == "lint"
Requires-Dist: googletrans==4.0.0rc1 ; extra == "test"
Requires-Dist: pytest-cov ; extra == "test"
Requires-Dist: pytest-xdist ; extra == "test"
Requires-Dist: pytest ; extra == "test"
Project-URL: Source, https://github.com/orsinium-labs/l10n
Provides-Extra: cli
Provides-Extra: docs
Provides-Extra: lint
Provides-Extra: test
